app/__init__.py
app/config.py
app/embedder.py
app/learner.py
app/llm_interface.py
app/mcp_server.py
app/processor.py
app/retriever.py
app/watcher.py
wireshark_rag_analyst-0.1.0.dist-info/licenses/LICENSE
wireshark_rag_analyst-0.1.0.dist-info/METADATA
wireshark_rag_analyst-0.1.0.dist-info/WHEEL
wireshark_rag_analyst-0.1.0.dist-info/entry_points.txt
wireshark_rag_analyst-0.1.0.dist-info/top_level.txt
wireshark_rag_analyst-0.1.0.dist-info/RECORD
