Metadata-Version: 2.4
Name: wireshark-rag-analyst
Version: 0.1.0
Summary: Local self-learning RAG system for Wireshark logs
Author: PranavK pkbythebay29
Author-email: pkbythebay29 <kannan@haztechrisk.org>
License: MIT
Requires-Python: >=3.8
License-File: LICENSE
Requires-Dist: pyyaml
Requires-Dist: watchdog
Requires-Dist: sentence-transformers
Requires-Dist: faiss-cpu
Requires-Dist: ollama
Dynamic: license-file
